myLepFT/__init__.py
myLepFT/myLepFT.py
myLepFT-1.0.1.dist-info/METADATA
myLepFT-1.0.1.dist-info/WHEEL
myLepFT-1.0.1.dist-info/top_level.txt
myLepFT-1.0.1.dist-info/RECORD
