Metadata-Version: 2.1
Name: myLepFT
Version: 1.0.1
Summary: To get Force/Torque sensor data through USB.
Author: Toshihiro Nishimura
Author-email: tnishimura@se.kanazawa-u.ac.jp
License: MIT
Requires-Dist: pyserial
Requires-Dist: numpy
